{
 "name": "cluster3a_1 avg",
 "relations": [
  {"name": "cn", "basetable": "company_name", "cardinality": 48302, "unfilteredCardinality": 234997},
  {"name": "ct", "basetable": "company_type", "cardinality": 1, "unfilteredCardinality": 4},
  {"name": "k", "basetable": "keyword", "cardinality": 1, "unfilteredCardinality": 134170},
  {"name": "lt", "basetable": "link_type", "cardinality": 2, "unfilteredCardinality": 18},
  {"name": "mc", "basetable": "movie_companies", "cardinality": 1.27199e+06, "unfilteredCardinality": 2.60913e+06},
  {"name": "mk", "basetable": "movie_keyword", "cardinality": 4.52393e+06, "unfilteredCardinality": 4.52393e+06},
  {"name": "ml", "basetable": "movie_link", "cardinality": 29997, "unfilteredCardinality": 29997},
  {"name": "t", "basetable": "title", "cardinality": 910581, "unfilteredCardinality": 2.52831e+06}
 ],
 "joins": [
  {"relations": ["lt", "ml"], "primaryKeySide": "lt"},
  {"relations": ["mc", "cn"], "primaryKeySide": "cn"},
  {"relations": ["mc", "ct"], "primaryKeySide": "ct"},
  {"relations": ["mk", "k"], "primaryKeySide": "k"},
  {"relations": ["mk", "mc"]},
  {"relations": ["ml", "mc"]},
  {"relations": ["ml", "mk"]},
  {"relations": ["ml", "t"], "primaryKeySide": "t"},
  {"relations": ["t", "mc"], "primaryKeySide": "t"},
  {"relations": ["t", "mk"], "primaryKeySide": "t"}
 ],
 "sizes": [
  {"relations": ["cn", "mc"], "cardinality": 240875},
  {"relations": ["ct", "mc"], "cardinality": 1.19393e+06},
  {"relations": ["k", "mk"], "cardinality": 10544},
  {"relations": ["lt", "ml"], "cardinality": 2315},
  {"relations": ["mc", "mk"], "cardinality": 6.71922e+06},
  {"relations": ["mc", "ml"], "cardinality": 43026},
  {"relations": ["mc", "t"], "cardinality": 546306},
  {"relations": ["mk", "ml"], "cardinality": 288192},
  {"relations": ["mk", "t"], "cardinality": 2.0113e+06},
  {"relations": ["ml", "t"], "cardinality": 13627},
  {"relations": ["cn", "ct", "mc"], "cardinality": 224256},
  {"relations": ["cn", "mc", "mk"], "cardinality": 1.48354e+06},
  {"relations": ["cn", "mc", "ml"], "cardinality": 3079},
  {"relations": ["cn", "mc", "t"], "cardinality": 95217},
  {"relations": ["ct", "mc", "mk"], "cardinality": 5.97529e+06},
  {"relations": ["ct", "mc", "ml"], "cardinality": 36283},
  {"relations": ["ct", "mc", "t"], "cardinality": 500448},
  {"relations": ["k", "mc", "mk"], "cardinality": 14331},
  {"relations": ["k", "mk", "ml"], "cardinality": 251},
  {"relations": ["k", "mk", "t"], "cardinality": 5541},
  {"relations": ["lt", "mc", "ml"], "cardinality": 5069},
  {"relations": ["lt", "mk", "ml"], "cardinality": 17543},
  {"relations": ["lt", "ml", "t"], "cardinality": 1332},
  {"relations": ["mc", "mk", "ml"], "cardinality": 732182},
  {"relations": ["mc", "mk", "t"], "cardinality": 3.18548e+06},
  {"relations": ["mc", "ml", "t"], "cardinality": 25214},
  {"relations": ["mk", "ml", "t"], "cardinality": 170868},
  {"relations": ["cn", "ct", "mc", "mk"], "cardinality": 1.33752e+06},
  {"relations": ["cn", "ct", "mc", "ml"], "cardinality": 2801},
  {"relations": ["cn", "ct", "mc", "t"], "cardinality": 86330},
  {"relations": ["cn", "k", "mc", "mk"], "cardinality": 2802},
  {"relations": ["cn", "lt", "mc", "ml"], "cardinality": 1200},
  {"relations": ["cn", "mc", "mk", "ml"], "cardinality": 49014},
  {"relations": ["cn", "mc", "mk", "t"], "cardinality": 682359},
  {"relations": ["cn", "mc", "ml", "t"], "cardinality": 1860},
  {"relations": ["ct", "k", "mc", "mk"], "cardinality": 11915},
  {"relations": ["ct", "lt", "mc", "ml"], "cardinality": 4393},
  {"relations": ["ct", "mc", "mk", "ml"], "cardinality": 610301},
  {"relations": ["ct", "mc", "mk", "t"], "cardinality": 2.69398e+06},
  {"relations": ["ct", "mc", "ml", "t"], "cardinality": 19453},
  {"relations": ["k", "lt", "mk", "ml"], "cardinality": 199},
  {"relations": ["k", "mc", "mk", "ml"], "cardinality": 1173},
  {"relations": ["k", "mc", "mk", "t"], "cardinality": 8138},
  {"relations": ["k", "mk", "ml", "t"], "cardinality": 199},
  {"relations": ["lt", "mc", "mk", "ml"], "cardinality": 54010},
  {"relations": ["lt", "mc", "ml", "t"], "cardinality": 3313},
  {"relations": ["lt", "mk", "ml", "t"], "cardinality": 12059},
  {"relations": ["mc", "mk", "ml", "t"], "cardinality": 437931},
  {"relations": ["cn", "ct", "k", "mc", "mk"], "cardinality": 2293},
  {"relations": ["cn", "ct", "lt", "mc", "ml"], "cardinality": 1152},
  {"relations": ["cn", "ct", "mc", "mk", "ml"], "cardinality": 40379},
  {"relations": ["cn", "ct", "mc", "mk", "t"], "cardinality": 590369},
  {"relations": ["cn", "ct", "mc", "ml", "t"], "cardinality": 1659},
  {"relations": ["cn", "k", "mc", "mk", "ml"], "cardinality": 452},
  {"relations": ["cn", "k", "mc", "mk", "t"], "cardinality": 1495},
  {"relations": ["cn", "lt", "mc", "mk", "ml"], "cardinality": 9430},
  {"relations": ["cn", "lt", "mc", "ml", "t"], "cardinality": 746},
  {"relations": ["cn", "mc", "mk", "ml", "t"], "cardinality": 29192},
  {"relations": ["ct", "k", "mc", "mk", "ml"], "cardinality": 1052},
  {"relations": ["ct", "k", "mc", "mk", "t"], "cardinality": 6646},
  {"relations": ["ct", "lt", "mc", "mk", "ml"], "cardinality": 45210},
  {"relations": ["ct", "lt", "mc", "ml", "t"], "cardinality": 2794},
  {"relations": ["ct", "mc", "mk", "ml", "t"], "cardinality": 330899},
  {"relations": ["k", "lt", "mc", "mk", "ml"], "cardinality": 1021},
  {"relations": ["k", "lt", "mk", "ml", "t"], "cardinality": 152},
  {"relations": ["k", "mc", "mk", "ml", "t"], "cardinality": 845},
  {"relations": ["lt", "mc", "mk", "ml", "t"], "cardinality": 40132},
  {"relations": ["cn", "ct", "k", "mc", "mk", "ml"], "cardinality": 422},
  {"relations": ["cn", "ct", "k", "mc", "mk", "t"], "cardinality": 1292},
  {"relations": ["cn", "ct", "lt", "mc", "mk", "ml"], "cardinality": 8713},
  {"relations": ["cn", "ct", "lt", "mc", "ml", "t"], "cardinality": 698},
  {"relations": ["cn", "ct", "mc", "mk", "ml", "t"], "cardinality": 26096},
  {"relations": ["cn", "k", "lt", "mc", "mk", "ml"], "cardinality": 422},
  {"relations": ["cn", "k", "mc", "mk", "ml", "t"], "cardinality": 360},
  {"relations": ["cn", "lt", "mc", "mk", "ml", "t"], "cardinality": 7580},
  {"relations": ["ct", "k", "lt", "mc", "mk", "ml"], "cardinality": 962},
  {"relations": ["ct", "k", "mc", "mk", "ml", "t"], "cardinality": 742},
  {"relations": ["ct", "lt", "mc", "mk", "ml", "t"], "cardinality": 32130},
  {"relations": ["k", "lt", "mc", "mk", "ml", "t"], "cardinality": 705},
  {"relations": ["cn", "ct", "k", "lt", "mc", "mk", "ml"], "cardinality": 402},
  {"relations": ["cn", "ct", "k", "mc", "mk", "ml", "t"], "cardinality": 330},
  {"relations": ["cn", "ct", "lt", "mc", "mk", "ml", "t"], "cardinality": 6863},
  {"relations": ["cn", "k", "lt", "mc", "mk", "ml", "t"], "cardinality": 330},
  {"relations": ["ct", "k", "lt", "mc", "mk", "ml", "t"], "cardinality": 664},
  {"relations": ["cn", "ct", "k", "lt", "mc", "mk", "ml", "t"], "cardinality": 310}
 ]
}
